{
	"sources": [
		{
			"type": "single",
			"resource": "server:item/strawberry_daifuku"
		},
		{
			"type": "single",
			"resource": "server:item/blue_curacao_soda"
		},
		{
			"type": "single",
			"resource": "server:item/omelet_rice"
		},
		{
			"type": "single",
			"resource": "server:item/pudding"
		},
		{
			"type": "single",
			"resource": "server:item/pizza"
		},
		{
			"type": "single",
			"resource": "server:item/mrt_ticket"
		},
		{
			"type": "single",
			"resource": "server:item/slime_fries"
		},
		{
			"type": "single",
			"resource": "server:item/slime_hamburger"
		},
		{
			"type": "single",
			"resource": "server:item/slime_cola"
		},
		{
			"type": "single",
			"resource": "server:item/banana"
		},{
			"type": "single",
			"resource": "server:item/banana_peel"
		},{
			"type": "single",
			"resource": "server:item/fried_banana_peel"
		},{
			"type": "single",
			"resource": "server:item/green_banana"
		},{
			"type": "single",
			"resource": "server:item/spotted_banana"
		},{
			"type": "single",
			"resource": "server:item/spicy_rabbit_head"
		},{
			"type": "single",
			"resource": "server:item/cat_food_can"
		},{
			"type": "single",
			"resource": "server:item/dog_food_can"
		}
	]
}
